basecore/__init__.py
basecore/config/__init__.py
basecore/config/config_dict.py
basecore/engine/__init__.py
basecore/engine/evaluator.py
basecore/engine/hooks.py
basecore/engine/lr_scheduler.py
basecore/engine/progress.py
basecore/engine/solver.py
basecore/engine/tester.py
basecore/engine/trainer.py
basecore/network/__init__.py
basecore/network/activation.py
basecore/network/module.py
basecore/network/norm.py
basecore/network/wrapper.py
basecore/utils/__init__.py
basecore/utils/checkpoint.py
basecore/utils/dist.py
basecore/utils/env_utils.py
basecore/utils/file.py
basecore/utils/import_utils.py
basecore/utils/inspector.py
basecore/utils/logger.py
basecore/utils/metric.py
basecore/utils/registry.py
basecore/utils/setup_env.py
basecore/utils/wrapper.py
tests/__init__.py
tests/test_configs.py
tests/test_layers.py
tests/test_lr_scheduler.py
tests/test_progress.py
basecore-0.1.10.dist-info/LICENSE
basecore-0.1.10.dist-info/METADATA
basecore-0.1.10.dist-info/WHEEL
basecore-0.1.10.dist-info/top_level.txt
basecore-0.1.10.dist-info/RECORD
