Metadata-Version: 2.1
Name: basecore
Version: 0.1.10
Summary: pack of megvii base team common used logic based on megengine
Author: wangfeng02
Author-email: wangfeng02@megvii.com
Classifier: Programming Language :: Python :: 3
Classifier: Operating System :: OS Independent
License-File: LICENSE
Requires-Dist: megfile
Requires-Dist: colorama
Requires-Dist: numpy
Requires-Dist: pyyaml
Requires-Dist: loguru
Requires-Dist: easydict
Requires-Dist: tabulate
